hedgehog/__init__.py
hedgehog/base.py
hedgehog/server.py
hedgehog/steam_cmd.py
hedgehog/tools.py
hedgehog-0.2.3.dist-info/DESCRIPTION.rst
hedgehog-0.2.3.dist-info/METADATA
hedgehog-0.2.3.dist-info/RECORD
hedgehog-0.2.3.dist-info/WHEEL
hedgehog-0.2.3.dist-info/metadata.json
hedgehog-0.2.3.dist-info/top_level.txt
