Metadata-Version: 2.0
Name: hedgehog
Version: 0.2.3
Summary: library for deploy SteamCMD and game servers
Home-page: https://github.com/k0st1an/hedgehog
Author: Konstantin Kruglov
Author-email: kruglovk@gmail.com
License: Apache License Version 2.0
Platform: UNKNOWN
Classifier: Development Status :: 3 - Alpha
Classifier: License :: OSI Approved :: Apache Software License
Classifier: Programming Language :: Python :: 3 :: Only
Classifier: Operating System :: POSIX :: Linux
Requires-Dist: requests (==2.13.0)
